[
    {
        "Group": "Street",
        "Variant": "Car.1",
        "Name": "Mini Car",
        "Acceleration": 3,
        "TopSpeed": 35,
        "Width": 4,
        "Height": 3,
        "Map": [
            "^&:^",
            "+@_+",
            "|TT|"
        ],
        "Legend": {
            "|": "SmallWheel;Taillight",
            "&": "LightFrame;SmallEngine;VehicleBodyPanel",
            ":": "LightFrame;SmallBattery;VehicleBodyPanel",
            "^": "LightFrame;Headlight",
            "+": "LightFrame;VehicleDoor",
            "@": "LightFrame;VehicleSeat;VehicleControls",
            "_": "LightFrame;VehicleSeat",
            "T": "LightFrame;VehicleTrunk",
            "#": "LightFrame;VehicleBodyPanel"
        }
    },
    {
        "Group": "Street",
        "Variant": "Car.2",
        "Name": "Mini Coup",
        "Acceleration": 3.5,
        "TopSpeed": 60,
        "Width": 4,
        "Height": 4,
        "Map": [
            "^&:^",
            "+@_+",
            "#__#",
            "|TT|"
        ],
        "Legend": {
            "|": "SmallWheel;Taillight",
            "&": "LightFrame;SmallEngine;VehicleBodyPanel",
            ":": "LightFrame;SmallBattery;VehicleBodyPanel",
            "^": "LightFrame;Headlight",
            "+": "LightFrame;VehicleDoor",
            "@": "LightFrame;VehicleSeat;VehicleControls",
            "_": "LightFrame;VehicleSeat",
            "T": "LightFrame;VehicleTrunk",
            "#": "LightFrame;VehicleBodyPanel"
        }
    },
    {
        "Group": "Street",
        "Variant": "Car.3",
        "Name": "Sports Coup",
        "Acceleration": 10,
        "TopSpeed": 120,
        "Width": 4,
        "Height": 5,
        "Map": [
            "^##^",
            "#&:#",
            "+@_+",
            "#__#",
            "|TT|"
        ],
        "Legend": {
            "|": "SmallWheel;Taillight",
            "&": "LightFrame;SmallEngine;VehicleBodyPanel",
            ":": "LightFrame;SmallBattery;VehicleBodyPanel",
            "^": "LightFrame;Headlight",
            "+": "LightFrame;VehicleDoor",
            "@": "LightFrame;VehicleSeat;VehicleControls",
            "_": "LightFrame;VehicleSeat",
            "T": "LightFrame;VehicleTrunk",
            "#": "LightFrame;VehicleBodyPanel"
        }
    }
]